ytpa_utils/__init__.py
ytpa_utils/constants.py
ytpa_utils/df_utils.py
ytpa_utils/gensim_utils.py
ytpa_utils/io_utils.py
ytpa_utils/misc_utils.py
ytpa_utils/np_utils.py
ytpa_utils/sql_utils.py
ytpa_utils/time_utils.py
ytpa_utils/val_utils.py
ytpa_utils-0.1.16.dist-info/METADATA
ytpa_utils-0.1.16.dist-info/WHEEL
ytpa_utils-0.1.16.dist-info/RECORD
