Metadata-Version: 2.1
Name: ytpa-utils
Version: 0.1.16
Summary: Utils for the YouTube Predictive Analytics system
License: MIT
Author: Johannes Traa
Requires-Python: >=3.11.5,<4.0.0
Classifier: License :: OSI Approved :: MIT License
Classifier: Programming Language :: Python :: 3
Requires-Dist: numpy (>=1.25.2,<2.0.0)
Requires-Dist: pandas (>=2.0.3,<3.0.0)
